china_beancount_importers/__init__.py
china_beancount_importers/wechat.py
china_beancount_importers-0.0.5.dist-info/licenses/LICENSE
china_beancount_importers-0.0.5.dist-info/WHEEL
china_beancount_importers-0.0.5.dist-info/METADATA
china_beancount_importers-0.0.5.dist-info/RECORD
